{"course":{"id":44792,"avg":3.722,"DR":7,"subject":"ARCH","C+":0,"C-":0,"title":"Faculty Research Seminar","A+":0,"A-":10,"A":11,"C":0,"B":3,"D":0,"F":0,"W":0,"instructors":"Anselmo Canfora, Maurice Cox, Melissa Goldman, Nana Last","class":"ARCH5590","D-":0,"D+":0,"B-":1,"B+":5,"students":37,"std":0.217416650696307},"sections":[{"id":30229,"semester":"Fall2012","DR":0,"subject":"ARCH","C+":0,"C-":0,"title":"Faculty Research Seminar","A+":0,"A-":0,"gpa":3.78,"A":0,"C":0,"B":0,"D":0,"F":0,"W":0,"instructor":"Anselmo Canfora","class":"ARCH5590","D-":0,"D+":0,"B-":0,"B+":0,"section":"3"},{"id":77392,"semester":"Spring2012","DR":0,"subject":"ARCH","C+":0,"C-":0,"title":"Faculty Research Seminar","A+":0,"A-":0,"gpa":3.91,"A":0,"C":0,"B":0,"D":0,"F":0,"W":0,"instructor":"Maurice Cox","class":"ARCH5590","D-":0,"D+":0,"B-":0,"B+":0,"section":"3"},{"id":123629,"semester":"Spring2017","DR":5,"subject":"ARCH","C+":0,"C-":0,"title":"Faculty Research Seminar","A+":0,"A-":6,"gpa":3.65,"A":3,"C":0,"B":1,"D":0,"F":0,"W":0,"instructor":"Anselmo Canfora","class":"ARCH5590","D-":0,"D+":0,"B-":0,"B+":2,"section":"3"},{"id":125721,"semester":"Spring2017","DR":0,"subject":"ARCH","C+":0,"C-":0,"title":"Faculty Research Seminar","A+":0,"A-":1,"gpa":3.89,"A":7,"C":0,"B":0,"D":0,"F":0,"W":0,"instructor":"Melissa Goldman","class":"ARCH5590","D-":0,"D+":0,"B-":0,"B+":1,"section":"2"},{"id":127560,"semester":"Spring2017","DR":2,"subject":"ARCH","C+":0,"C-":0,"title":"Faculty Research Seminar","A+":0,"A-":3,"gpa":3.38,"A":1,"C":0,"B":2,"D":0,"F":0,"W":0,"instructor":"Nana Last","class":"ARCH5590","D-":0,"D+":0,"B-":1,"B+":2,"section":"1"}]}