{"course":{"id":45031,"avg":3.64,"DR":7,"subject":"ARCH","C+":0,"C-":0,"title":"Professional Practices","A+":3,"A-":77,"A":91,"C":1,"B":39,"D":0,"F":0,"W":1,"instructors":"Richard Price, Karen Van Lengen, Margaret Cavenagh","class":"ARCH8480","D-":0,"D+":0,"B-":8,"B+":27,"students":254,"std":0.162304827848272},"sections":[{"id":34961,"semester":"Fall2012","DR":0,"subject":"ARCH","C+":0,"C-":0,"title":"Professionl Ethics & Communctn","A+":0,"A-":18,"gpa":3.7,"A":1,"C":0,"B":0,"D":0,"F":0,"W":0,"instructor":"Richard Price","class":"ARCH8480","D-":0,"D+":0,"B-":0,"B+":1,"section":"1"},{"id":45071,"semester":"Fall2013","DR":6,"subject":"ARCH","C+":0,"C-":0,"title":"Introduction to Engineering","A+":0,"A-":0,"gpa":3.52,"A":23,"C":1,"B":18,"D":0,"F":0,"W":0,"instructor":"Karen Van Lengen","class":"ARCH8480","D-":0,"D+":0,"B-":0,"B+":0,"section":"1"},{"id":54100,"semester":"Fall2014","DR":0,"subject":"ARCH","C+":0,"C-":0,"title":"Professionl Ethics & Communctn","A+":0,"A-":18,"gpa":3.66,"A":5,"C":0,"B":2,"D":0,"F":0,"W":0,"instructor":"Karen Van Lengen","class":"ARCH8480","D-":0,"D+":0,"B-":0,"B+":3,"section":"1"},{"id":63676,"semester":"Fall2015","DR":0,"subject":"ARCH","C+":0,"C-":0,"title":"Professionl Ethics & Communctn","A+":3,"A-":3,"gpa":3.73,"A":10,"C":0,"B":2,"D":0,"F":0,"W":0,"instructor":"Karen Van Lengen","class":"ARCH8480","D-":0,"D+":0,"B-":1,"B+":2,"section":"1"},{"id":82640,"semester":"Spring2012","DR":0,"subject":"ARCH","C+":0,"C-":0,"title":"Professionl Ethics & Communctn","A+":0,"A-":12,"gpa":3.87,"A":19,"C":0,"B":0,"D":0,"F":0,"W":0,"instructor":"Richard Price","class":"ARCH8480","D-":0,"D+":0,"B-":0,"B+":1,"section":"1"},{"id":131769,"semester":"Spring2017","DR":0,"subject":"ARCH","C+":0,"C-":0,"title":"Professionl Ethics & Communctn","A+":0,"A-":10,"gpa":3.63,"A":6,"C":0,"B":1,"D":0,"F":0,"W":0,"instructor":"Karen Van Lengen","class":"ARCH8480","D-":0,"D+":0,"B-":0,"B+":7,"section":"1"},{"id":204327,"semester":"Spring2018","DR":1,"subject":"ARCH","C+":0,"C-":0,"title":"Professionl Ethics & Communctn","A+":0,"A-":9,"gpa":3.69,"A":20,"C":0,"B":3,"D":0,"F":0,"W":1,"instructor":"Karen Van Lengen","class":"ARCH8480","D-":0,"D+":0,"B-":2,"B+":6,"section":"1"},{"id":209251,"semester":"Spring2019","DR":0,"subject":"ARCH","C+":0,"C-":0,"title":"Professional Practices","A+":0,"A-":7,"gpa":3.32,"A":7,"C":0,"B":13,"D":0,"F":0,"W":0,"instructor":"Margaret Cavenagh","class":"ARCH8480","D-":0,"D+":0,"B-":5,"B+":7,"section":"1"}]}