{"course":{"id":47915,"avg":3.555,"DR":23,"subject":"COMM","C+":0,"C-":0,"title":"Digital Innovation","A+":2,"A-":26,"A":28,"C":0,"B":13,"D":0,"F":0,"W":0,"instructors":"Stefano Grazioli","class":"COMM4250","D-":0,"D+":0,"B-":1,"B+":32,"students":125,"std":0.0264575131106459},"sections":[{"id":106113,"semester":"Spring2015","DR":4,"subject":"COMM","C+":0,"C-":0,"title":"Digital Innovation","A+":0,"A-":6,"gpa":3.52,"A":3,"C":0,"B":4,"D":0,"F":0,"W":0,"instructor":"Stefano Grazioli","class":"COMM4250","D-":0,"D+":0,"B-":0,"B+":2,"section":"1"},{"id":116022,"semester":"Spring2016","DR":3,"subject":"COMM","C+":0,"C-":0,"title":"Digital Innovation","A+":0,"A-":4,"gpa":3.55,"A":5,"C":0,"B":1,"D":0,"F":0,"W":0,"instructor":"Stefano Grazioli","class":"COMM4250","D-":0,"D+":0,"B-":1,"B+":6,"section":"1"},{"id":125810,"semester":"Spring2017","DR":12,"subject":"COMM","C+":0,"C-":0,"title":"Digital Innovation","A+":1,"A-":12,"gpa":3.58,"A":7,"C":0,"B":0,"D":0,"F":0,"W":0,"instructor":"Stefano Grazioli","class":"COMM4250","D-":0,"D+":0,"B-":0,"B+":17,"section":"1"},{"id":202825,"semester":"Spring2018","DR":4,"subject":"COMM","C+":0,"C-":0,"title":"Digital Innovation","A+":1,"A-":4,"gpa":3.57,"A":13,"C":0,"B":8,"D":0,"F":0,"W":0,"instructor":"Stefano Grazioli","class":"COMM4250","D-":0,"D+":0,"B-":0,"B+":7,"section":"1"}]}