{"course":{"id":44250,"avg":3.27333333333333,"DR":160,"subject":"HIEU","C+":15,"C-":2,"title":"Origins of Contemporary Thgt","A+":10,"A-":47,"A":64,"C":10,"B":44,"D":0,"F":3,"W":13,"instructors":"Allan Megill","class":"HIEU3802","D-":0,"D+":1,"B-":37,"B+":40,"students":444,"std":0.137792113949481},"sections":[{"id":27435,"semester":"Fall2011","DR":30,"subject":"HIEU","C+":1,"C-":0,"title":"Origins of Contemporary Thgt","A+":2,"A-":9,"gpa":3.12,"A":7,"C":7,"B":9,"D":0,"F":0,"W":0,"instructor":"Allan Megill","class":"HIEU3802","D-":0,"D+":0,"B-":10,"B+":4,"section":"100"},{"id":42485,"semester":"Fall2013","DR":28,"subject":"HIEU","C+":4,"C-":0,"title":"Origins of Contemporary Thgt","A+":2,"A-":7,"gpa":3.15,"A":6,"C":1,"B":12,"D":0,"F":1,"W":4,"instructor":"Allan Megill","class":"HIEU3802","D-":0,"D+":0,"B-":5,"B+":6,"section":"100"},{"id":51441,"semester":"Fall2014","DR":30,"subject":"HIEU","C+":6,"C-":2,"title":"Origins of Contemporary Thgt","A+":1,"A-":8,"gpa":3.18,"A":8,"C":0,"B":5,"D":0,"F":0,"W":4,"instructor":"Allan Megill","class":"HIEU3802","D-":0,"D+":0,"B-":7,"B+":7,"section":"1"},{"id":118584,"semester":"Spring2016","DR":26,"subject":"HIEU","C+":1,"C-":0,"title":"Origins of Contemporary Thgt","A+":2,"A-":4,"gpa":3.39,"A":13,"C":1,"B":2,"D":0,"F":0,"W":0,"instructor":"Allan Megill","class":"HIEU3802","D-":0,"D+":1,"B-":6,"B+":11,"section":"1"},{"id":185760,"semester":"Fall2017","DR":25,"subject":"HIEU","C+":2,"C-":0,"title":"Origins of Contemporary Thgt","A+":1,"A-":9,"gpa":3.37,"A":16,"C":1,"B":10,"D":0,"F":1,"W":2,"instructor":"Allan Megill","class":"HIEU3802","D-":0,"D+":0,"B-":4,"B+":3,"section":"1"},{"id":206654,"semester":"Fall2018","DR":21,"subject":"HIEU","C+":1,"C-":0,"title":"Origins of Contemporary Thgt","A+":2,"A-":10,"gpa":3.43,"A":14,"C":0,"B":6,"D":0,"F":1,"W":3,"instructor":"Allan Megill","class":"HIEU3802","D-":0,"D+":0,"B-":5,"B+":9,"section":"1"}]}