{"course":{"id":44204,"avg":3.30954545454545,"DR":59,"subject":"JAPN","C+":6,"C-":8,"title":"Second-Year Japanese I","A+":1,"A-":71,"A":65,"C":12,"B":43,"D":2,"F":2,"W":1,"instructors":"Tomoko Marshall, Miyuki Kamiya, Mieko Kawai","class":"JAPN2010","D-":0,"D+":1,"B-":30,"B+":56,"students":349,"std":0.23554349052932},"sections":[{"id":27359,"semester":"Fall2011","DR":0,"subject":"JAPN","C+":0,"C-":0,"title":"Second-Year Japanese I","A+":0,"A-":0,"gpa":3.72,"A":0,"C":0,"B":0,"D":0,"F":0,"W":0,"instructor":"Tomoko Marshall","class":"JAPN2010","D-":0,"D+":0,"B-":0,"B+":0,"section":"1"},{"id":27360,"semester":"Fall2011","DR":2,"subject":"JAPN","C+":0,"C-":1,"title":"Second-Year Japanese I","A+":0,"A-":4,"gpa":3.13,"A":2,"C":0,"B":4,"D":1,"F":0,"W":0,"instructor":"Tomoko Marshall","class":"JAPN2010","D-":0,"D+":0,"B-":1,"B+":3,"section":"3"},{"id":27361,"semester":"Fall2011","DR":0,"subject":"JAPN","C+":0,"C-":1,"title":"Second-Year Japanese I","A+":0,"A-":3,"gpa":3.17,"A":4,"C":1,"B":1,"D":1,"F":0,"W":0,"instructor":"Tomoko Marshall","class":"JAPN2010","D-":0,"D+":0,"B-":1,"B+":4,"section":"2"},{"id":33753,"semester":"Fall2012","DR":1,"subject":"JAPN","C+":1,"C-":0,"title":"Second-Year Japanese I","A+":0,"A-":1,"gpa":3.54,"A":8,"C":0,"B":2,"D":0,"F":0,"W":0,"instructor":"Tomoko Marshall","class":"JAPN2010","D-":0,"D+":0,"B-":1,"B+":3,"section":"2"},{"id":33757,"semester":"Fall2012","DR":5,"subject":"JAPN","C+":0,"C-":1,"title":"Second-Year Japanese I","A+":0,"A-":2,"gpa":3.06,"A":1,"C":1,"B":1,"D":0,"F":0,"W":0,"instructor":"Tomoko Marshall","class":"JAPN2010","D-":0,"D+":0,"B-":2,"B+":4,"section":"3"},{"id":33761,"semester":"Fall2012","DR":3,"subject":"JAPN","C+":0,"C-":2,"title":"Second-Year Japanese I","A+":0,"A-":2,"gpa":2.75,"A":2,"C":2,"B":1,"D":0,"F":0,"W":0,"instructor":"Tomoko Marshall","class":"JAPN2010","D-":0,"D+":1,"B-":2,"B+":1,"section":"1"},{"id":41240,"semester":"Fall2013","DR":3,"subject":"JAPN","C+":0,"C-":0,"title":"Second-Year Japanese I","A+":0,"A-":5,"gpa":3.58,"A":4,"C":0,"B":1,"D":0,"F":0,"W":0,"instructor":"Miyuki Kamiya","class":"JAPN2010","D-":0,"D+":0,"B-":1,"B+":3,"section":"1"},{"id":41244,"semester":"Fall2013","DR":2,"subject":"JAPN","C+":0,"C-":0,"title":"Second-Year Japanese I","A+":1,"A-":3,"gpa":3.55,"A":1,"C":0,"B":0,"D":0,"F":0,"W":0,"instructor":"Miyuki Kamiya","class":"JAPN2010","D-":0,"D+":0,"B-":1,"B+":2,"section":"3"},{"id":41249,"semester":"Fall2013","DR":4,"subject":"JAPN","C+":0,"C-":1,"title":"Second-Year Japanese I","A+":0,"A-":3,"gpa":3.25,"A":4,"C":0,"B":3,"D":0,"F":0,"W":0,"instructor":"Miyuki Kamiya","class":"JAPN2010","D-":0,"D+":0,"B-":4,"B+":2,"section":"2"},{"id":50112,"semester":"Fall2014","DR":3,"subject":"JAPN","C+":2,"C-":0,"title":"Second-Year Japanese I","A+":0,"A-":4,"gpa":3.05,"A":3,"C":1,"B":2,"D":0,"F":1,"W":0,"instructor":"Mieko Kawai","class":"JAPN2010","D-":0,"D+":0,"B-":0,"B+":1,"section":"1"},{"id":50117,"semester":"Fall2014","DR":6,"subject":"JAPN","C+":0,"C-":0,"title":"Second-Year Japanese I","A+":0,"A-":4,"gpa":3.32,"A":2,"C":1,"B":1,"D":0,"F":0,"W":0,"instructor":"Mieko Kawai","class":"JAPN2010","D-":0,"D+":0,"B-":2,"B+":2,"section":"2"},{"id":60589,"semester":"Fall2015","DR":5,"subject":"JAPN","C+":0,"C-":1,"title":"Second-Year Japanese I","A+":0,"A-":5,"gpa":3.13,"A":1,"C":1,"B":2,"D":0,"F":0,"W":0,"instructor":"Tomoko Marshall","class":"JAPN2010","D-":0,"D+":0,"B-":2,"B+":0,"section":"1"},{"id":60593,"semester":"Fall2015","DR":2,"subject":"JAPN","C+":0,"C-":0,"title":"Second-Year Japanese I","A+":0,"A-":4,"gpa":3.49,"A":5,"C":1,"B":3,"D":0,"F":0,"W":0,"instructor":"Tomoko Marshall","class":"JAPN2010","D-":0,"D+":0,"B-":0,"B+":2,"section":"2"},{"id":60597,"semester":"Fall2015","DR":0,"subject":"JAPN","C+":0,"C-":0,"title":"Second-Year Japanese I","A+":0,"A-":1,"gpa":3.21,"A":3,"C":1,"B":2,"D":0,"F":0,"W":1,"instructor":"Tomoko Marshall","class":"JAPN2010","D-":0,"D+":0,"B-":3,"B+":4,"section":"3"},{"id":70995,"semester":"Fall2016","DR":2,"subject":"JAPN","C+":0,"C-":0,"title":"Second-Year Japanese I","A+":0,"A-":5,"gpa":3.47,"A":2,"C":0,"B":2,"D":0,"F":0,"W":0,"instructor":"Tomoko Marshall","class":"JAPN2010","D-":0,"D+":0,"B-":1,"B+":3,"section":"1"},{"id":70999,"semester":"Fall2016","DR":4,"subject":"JAPN","C+":0,"C-":0,"title":"Second-Year Japanese I","A+":0,"A-":2,"gpa":3.37,"A":3,"C":0,"B":1,"D":0,"F":0,"W":0,"instructor":"Tomoko Marshall","class":"JAPN2010","D-":0,"D+":0,"B-":3,"B+":3,"section":"2"},{"id":185393,"semester":"Fall2017","DR":5,"subject":"JAPN","C+":0,"C-":0,"title":"Second-Year Japanese I","A+":0,"A-":5,"gpa":3.39,"A":1,"C":0,"B":5,"D":0,"F":0,"W":0,"instructor":"Mieko Kawai","class":"JAPN2010","D-":0,"D+":0,"B-":0,"B+":3,"section":"1"},{"id":185394,"semester":"Fall2017","DR":3,"subject":"JAPN","C+":1,"C-":0,"title":"Second-Year Japanese I","A+":0,"A-":5,"gpa":3.51,"A":5,"C":0,"B":0,"D":0,"F":0,"W":0,"instructor":"Mieko Kawai","class":"JAPN2010","D-":0,"D+":0,"B-":2,"B+":3,"section":"2"},{"id":185395,"semester":"Fall2017","DR":2,"subject":"JAPN","C+":0,"C-":0,"title":"Second-Year Japanese I","A+":0,"A-":5,"gpa":3.34,"A":3,"C":0,"B":1,"D":0,"F":1,"W":0,"instructor":"Mieko Kawai","class":"JAPN2010","D-":0,"D+":0,"B-":0,"B+":4,"section":"3"},{"id":206234,"semester":"Fall2018","DR":3,"subject":"JAPN","C+":0,"C-":1,"title":"Second-Year Japanese I","A+":0,"A-":2,"gpa":3.03,"A":1,"C":2,"B":5,"D":0,"F":0,"W":0,"instructor":"Mieko Kawai","class":"JAPN2010","D-":0,"D+":0,"B-":1,"B+":6,"section":"1"},{"id":206235,"semester":"Fall2018","DR":1,"subject":"JAPN","C+":1,"C-":0,"title":"Second-Year Japanese I","A+":0,"A-":4,"gpa":3.57,"A":7,"C":0,"B":2,"D":0,"F":0,"W":0,"instructor":"Mieko Kawai","class":"JAPN2010","D-":0,"D+":0,"B-":1,"B+":1,"section":"2"},{"id":206236,"semester":"Fall2018","DR":3,"subject":"JAPN","C+":1,"C-":0,"title":"Second-Year Japanese I","A+":0,"A-":2,"gpa":3.18,"A":3,"C":1,"B":4,"D":0,"F":0,"W":0,"instructor":"Mieko Kawai","class":"JAPN2010","D-":0,"D+":0,"B-":2,"B+":2,"section":"3"}]}