{"course":{"id":47948,"avg":3.9,"DR":0,"subject":"MATH","C+":0,"C-":0,"title":"Fiber Bundles","A+":0,"A-":0,"A":0,"C":0,"B":0,"D":0,"F":0,"W":0,"instructors":"Nicholas Kuhn","class":"MATH7830","D-":0,"D+":0,"B-":0,"B+":0,"students":0,"std":0},"sections":[{"id":107782,"semester":"Spring2015","DR":0,"subject":"MATH","C+":0,"C-":0,"title":"Fiber Bundles","A+":0,"A-":0,"gpa":3.9,"A":0,"C":0,"B":0,"D":0,"F":0,"W":0,"instructor":"Nicholas Kuhn","class":"MATH7830","D-":0,"D+":0,"B-":0,"B+":0,"section":"1"}]}