{"course":{"id":45907,"avg":3.455,"DR":18,"subject":"MDST","C+":0,"C-":0,"title":"Podcasting Radio Sound","A+":0,"A-":18,"A":6,"C":0,"B":11,"D":0,"F":0,"W":0,"instructors":"Elliot Majerczyk","class":"MDST2305","D-":0,"D+":0,"B-":1,"B+":23,"students":77,"std":0.193476958145753},"sections":[{"id":60508,"semester":"Fall2015","DR":9,"subject":"MDST","C+":0,"C-":0,"title":"Intro to Radio/Sound Product","A+":0,"A-":6,"gpa":3.45,"A":0,"C":0,"B":2,"D":0,"F":0,"W":0,"instructor":"Elliot Majerczyk","class":"MDST2305","D-":0,"D+":0,"B-":0,"B+":4,"section":"1"},{"id":70886,"semester":"Fall2016","DR":4,"subject":"MDST","C+":0,"C-":0,"title":"Podcasting Radio Sound","A+":0,"A-":4,"gpa":3.73,"A":5,"C":0,"B":0,"D":0,"F":0,"W":0,"instructor":"Elliot Majerczyk","class":"MDST2305","D-":0,"D+":0,"B-":0,"B+":3,"section":"1"},{"id":118234,"semester":"Spring2016","DR":3,"subject":"MDST","C+":0,"C-":0,"title":"Intro to Radio/Sound Product","A+":0,"A-":4,"gpa":3.31,"A":0,"C":0,"B":5,"D":0,"F":0,"W":0,"instructor":"Elliot Majerczyk","class":"MDST2305","D-":0,"D+":0,"B-":0,"B+":11,"section":"1"},{"id":128178,"semester":"Spring2017","DR":2,"subject":"MDST","C+":0,"C-":0,"title":"Podcasting Radio Sound","A+":0,"A-":4,"gpa":3.33,"A":1,"C":0,"B":4,"D":0,"F":0,"W":0,"instructor":"Elliot Majerczyk","class":"MDST2305","D-":0,"D+":0,"B-":1,"B+":5,"section":"1"}]}