{"course":{"id":46326,"avg":3.995,"DR":3,"subject":"MUBD","C+":0,"C-":0,"title":"Marching Band II","A+":0,"A-":0,"A":71,"C":0,"B":0,"D":0,"F":0,"W":0,"instructors":"William Pease, Andrew Koch","class":"MUBD2620","D-":0,"D+":0,"B-":0,"B+":0,"students":74,"std":0.00707106781186532},"sections":[{"id":72518,"semester":"Fall2016","DR":3,"subject":"MUBD","C+":0,"C-":0,"title":"Marching Band II","A+":0,"A-":0,"gpa":4,"A":71,"C":0,"B":0,"D":0,"F":0,"W":0,"instructor":"William Pease","class":"MUBD2620","D-":0,"D+":0,"B-":0,"B+":0,"section":"1"},{"id":185463,"semester":"Fall2017","DR":0,"subject":"MUBD","C+":0,"C-":0,"title":"Marching Band II","A+":0,"A-":0,"gpa":3.99,"A":0,"C":0,"B":0,"D":0,"F":0,"W":0,"instructor":"Andrew Koch","class":"MUBD2620","D-":0,"D+":0,"B-":0,"B+":0,"section":"1"}]}