{"course":{"id":44222,"avg":3.9675,"DR":7,"subject":"NURS","C+":0,"C-":0,"title":"Nursing Leadership in Action","A+":45,"A-":0,"A":0,"C":0,"B":0,"D":0,"F":0,"W":0,"instructors":"Carol Maxwell-Thompson","class":"NURS3003","D-":0,"D+":0,"B-":0,"B+":0,"students":52,"std":0.0518812747209113},"sections":[{"id":27389,"semester":"Fall2011","DR":0,"subject":"NURS","C+":0,"C-":0,"title":"Nursing Leadership in Action","A+":0,"A-":0,"gpa":3.89,"A":0,"C":0,"B":0,"D":0,"F":0,"W":0,"instructor":"Carol Maxwell-Thompson","class":"NURS3003","D-":0,"D+":0,"B-":0,"B+":0,"section":"1"},{"id":81476,"semester":"Spring2012","DR":0,"subject":"NURS","C+":0,"C-":0,"title":"Nursing Leadership in Action","A+":0,"A-":0,"gpa":3.99,"A":0,"C":0,"B":0,"D":0,"F":0,"W":0,"instructor":"Carol Maxwell-Thompson","class":"NURS3003","D-":0,"D+":0,"B-":0,"B+":0,"section":"1"},{"id":128456,"semester":"Spring2017","DR":7,"subject":"NURS","C+":0,"C-":0,"title":"Nursing Leadership in Action","A+":45,"A-":0,"gpa":4,"A":0,"C":0,"B":0,"D":0,"F":0,"W":0,"instructor":"Carol Maxwell-Thompson","class":"NURS3003","D-":0,"D+":0,"B-":0,"B+":0,"section":"1"},{"id":185717,"semester":"Fall2017","DR":0,"subject":"NURS","C+":0,"C-":0,"title":"Nursing Leadership in Action","A+":0,"A-":0,"gpa":3.99,"A":0,"C":0,"B":0,"D":0,"F":0,"W":0,"instructor":"Carol Maxwell-Thompson","class":"NURS3003","D-":0,"D+":0,"B-":0,"B+":0,"section":"1"}]}