{"course":{"id":46059,"avg":0,"DR":1,"subject":"PHAR","C+":0,"C-":0,"title":"Seminar in Pharmacology","A+":0,"A-":0,"A":0,"C":0,"B":0,"D":0,"F":0,"W":0,"instructors":"Mark Beenhakker","class":"PHAR7010","D-":0,"D+":0,"B-":0,"B+":0,"students":1,"std":0},"sections":[{"id":65402,"semester":"Fall2016","DR":0,"subject":"PHAR","C+":0,"C-":0,"title":"Seminar in Pharmacology","A+":0,"A-":0,"gpa":0,"A":0,"C":0,"B":0,"D":0,"F":0,"W":0,"instructor":"Mark Beenhakker","class":"PHAR7010","D-":0,"D+":0,"B-":0,"B+":0,"section":"1"},{"id":205194,"semester":"Fall2018","DR":1,"subject":"PHAR","C+":0,"C-":0,"title":"Seminar in Pharmacology","A+":0,"A-":0,"gpa":0,"A":0,"C":0,"B":0,"D":0,"F":0,"W":0,"instructor":"Mark Beenhakker","class":"PHAR7010","D-":0,"D+":0,"B-":0,"B+":0,"section":"1"}]}