{"course":{"id":45867,"avg":3.228,"DR":90,"subject":"PLPT","C+":5,"C-":3,"title":"Contemporary Political Thought","A+":1,"A-":44,"A":29,"C":5,"B":59,"D":0,"F":3,"W":5,"instructors":"Murad Idris, Christopher Lebron","class":"PLPT3030","D-":0,"D+":1,"B-":22,"B+":57,"students":321,"std":0.11861703081767},"sections":[{"id":59135,"semester":"Fall2015","DR":8,"subject":"PLPT","C+":2,"C-":0,"title":"Contemporary Political Thought","A+":0,"A-":8,"gpa":3.36,"A":4,"C":0,"B":4,"D":0,"F":0,"W":2,"instructor":"Murad Idris","class":"PLPT3030","D-":0,"D+":0,"B-":2,"B+":8,"section":"1"},{"id":69448,"semester":"Fall2016","DR":28,"subject":"PLPT","C+":1,"C-":0,"title":"Contemporary Political Thought","A+":0,"A-":9,"gpa":3.28,"A":9,"C":1,"B":15,"D":0,"F":0,"W":2,"instructor":"Murad Idris","class":"PLPT3030","D-":0,"D+":0,"B-":7,"B+":13,"section":"100"},{"id":80813,"semester":"Spring2012","DR":10,"subject":"PLPT","C+":0,"C-":0,"title":"Contemporary Political Thought","A+":0,"A-":7,"gpa":3.25,"A":2,"C":0,"B":8,"D":0,"F":1,"W":0,"instructor":"Christopher Lebron","class":"PLPT3030","D-":0,"D+":0,"B-":0,"B+":14,"section":"1"},{"id":116812,"semester":"Spring2016","DR":25,"subject":"PLPT","C+":2,"C-":0,"title":"Contemporary Political Thought","A+":1,"A-":12,"gpa":3.21,"A":6,"C":1,"B":20,"D":0,"F":1,"W":0,"instructor":"Murad Idris","class":"PLPT3030","D-":0,"D+":0,"B-":4,"B+":13,"section":"100"},{"id":126777,"semester":"Spring2017","DR":19,"subject":"PLPT","C+":0,"C-":3,"title":"Contemporary Political Thought","A+":0,"A-":8,"gpa":3.04,"A":8,"C":3,"B":12,"D":0,"F":1,"W":1,"instructor":"Murad Idris","class":"PLPT3030","D-":0,"D+":1,"B-":9,"B+":9,"section":"100"}]}